compressed_segmentation.cpython-310-darwin.so
compressed_segmentation-2.3.2.dist-info/RECORD
compressed_segmentation-2.3.2.dist-info/AUTHORS
compressed_segmentation-2.3.2.dist-info/WHEEL
compressed_segmentation-2.3.2.dist-info/LICENSE_JANELIA.txt
compressed_segmentation-2.3.2.dist-info/LICENSE_PYTHON.txt
compressed_segmentation-2.3.2.dist-info/entry_points.txt
compressed_segmentation-2.3.2.dist-info/pbr.json
compressed_segmentation-2.3.2.dist-info/top_level.txt
compressed_segmentation-2.3.2.dist-info/LICENSE.txt
compressed_segmentation-2.3.2.dist-info/METADATA
cseg_cli/__init__.py
cseg_cli/cli.py
