Metadata-Version: 2.1
Name: compressed_segmentation
Version: 2.3.2
Summary: Neuroglancer compressed_segmentation codec.
Home-page: https://github.com/janelia-flyem/compressedseg
Author: Jeremy Maitin-Shepard, Stephen Plaza, and William Silversmith
Author-email: ws9@princeton.edu
Classifier: Intended Audience :: Developers
Classifier: Development Status :: 4 - Beta
Classifier: License :: OSI Approved :: Apache Software License
Classifier: License :: OSI Approved :: BSD License
Classifier: Programming Language :: Python
Classifier: Programming Language :: Python :: 3
Classifier: Programming Language :: Python :: 3.7
Classifier: Programming Language :: Python :: 3.8
Classifier: Programming Language :: Python :: 3.9
Classifier: Programming Language :: Python :: 3.10
Classifier: Programming Language :: Python :: 3.11
Classifier: Topic :: Utilities
License-File: LICENSE.txt
License-File: LICENSE_JANELIA.txt
License-File: LICENSE_PYTHON.txt
License-File: AUTHORS
Requires-Dist: click
Requires-Dist: numpy
Requires-Dist: pytest
